{
    "_links": {
        "self": {
            "href": "http:\/\/default\/block\/8?_format=hal_json"
        },
        "type": {
            "href": "http:\/\/drupal.org\/rest\/type\/block_content\/teaser"
        },
        "http:\/\/drupal.org\/rest\/relation\/block_content\/teaser\/field_teaser_image": [
            {
                "href": "http:\/\/default\/file\/3389?_format=hal_json"
            }
        ]
    },
    "id": [
        {
            "value": "8"
        }
    ],
    "uuid": [
        {
            "value": "76e49bf8-4e9a-4172-b400-c1743e8dfc1d"
        }
    ],
    "revision_id": [
        {
            "value": "8"
        }
    ],
    "langcode": [
        {
            "value": "en",
            "lang": "en"
        }
    ],
    "type": [
        {
            "target_id": "teaser"
        }
    ],
    "info": [
        {
            "value": "Lindsey russell \u2018the wave runner\u2019",
            "lang": "en"
        }
    ],
    "changed": [
        {
            "value": "1478520014",
            "lang": "en"
        }
    ],
    "revision_created": [
        {
            "value": "1478518505"
        }
    ],
    "revision_translation_affected": [
        {
            "value": "1",
            "lang": "en"
        }
    ],
    "default_langcode": [
        {
            "value": "1",
            "lang": "en"
        }
    ],
    "body": [
        {
            "value": "<h3>Lindsey russell \u2018the wave runner\u2019<\/h3>\r\n",
            "format": "basic_html",
            "summary": "",
            "lang": "en"
        }
    ],
    "field_cw_link_target": [
        {
            "value": "1"
        }
    ],
    "field_teaser_bg_colour": [
        {
            "value": "bg--black"
        }
    ],
    "_embedded": {
        "http:\/\/drupal.org\/rest\/relation\/block_content\/teaser\/field_teaser_image": [
            {
                "_links": {
                    "self": {
                        "href": "http:\/\/default\/file\/3389?_format=hal_json"
                    },
                    "type": {
                        "href": "http:\/\/drupal.org\/rest\/type\/file\/image"
                    }
                },
                "uuid": [
                    {
                        "value": "acf75dc0-0415-4fb8-a40e-8d348ebb063e"
                    }
                ],
                "alt": "bg",
                "title": "",
                "width": "2340",
                "height": "1316"
            }
        ]
    },
    "field_teaser_img_bg": [
        {
            "value": "1"
        }
    ],
    "field_teaser_link_address": [
        {
            "value": "http:\/\/www.comicrelief.com\/"
        }
    ],
    "field_teaser_link_colour": [
        {
            "value": "btn--red"
        }
    ],
    "field_teaser_link_title": [
        {
            "value": "Find out"
        }
    ],
    "field_teaser_title": [
        {
            "value": "Lindsey russell \u2018the wave runner\u2019"
        }
    ],
    "field_teaser_you_tube_link": [
        {
            "value": "0"
        }
    ]
}